bbpylib/__init__.py
bbpylib/git.py
bbpylib/pip.py
bbpylib/process.py
bbpylib/repo.py
bbpylib/colab/Ed.py
bbpylib/colab/__init__.py
bbpylib/colab/auto.py
bbpylib/colab/tools.py
bbpylib/old/bbgit.py
bbpylib-0.1.17.dist-info/METADATA
bbpylib-0.1.17.dist-info/WHEEL
bbpylib-0.1.17.dist-info/licenses/LICENSE
bbpylib-0.1.17.dist-info/RECORD
