Metadata-Version: 2.4
Name: bbpylib
Version: 0.1.17
Summary: A personal Python utility library.
Author: Brandon Bennett
License: MIT
License-File: LICENSE
Requires-Python: >=3.9
